final_project_shopping_list/README.md
final_project_shopping_list/cli.py
final_project_shopping_list/count_sort_items.py
final_project_shopping_list/poetry.lock
final_project_shopping_list/print_items.py
final_project_shopping_list/read_file_items.py
final_project_shopping_list/shopping-list.txt
final_project_shopping_list/write_items_file.py
final_project_shopping_list-0.2.3.dist-info/METADATA
final_project_shopping_list-0.2.3.dist-info/WHEEL
final_project_shopping_list-0.2.3.dist-info/entry_points.txt
final_project_shopping_list-0.2.3.dist-info/RECORD
