Metadata-Version: 2.3
Name: final_project_shopping_list
Version: 0.2.3
Summary: Simple command line shopping list
Author: lascalaCanada
Author-email: lascala.canada@gmail.com
Requires-Python: >=3.9
Classifier: Programming Language :: Python :: 3
Classifier: Programming Language :: Python :: 3.9
Classifier: Programming Language :: Python :: 3.10
Classifier: Programming Language :: Python :: 3.11
Classifier: Programming Language :: Python :: 3.12
Classifier: Programming Language :: Python :: 3.13
